{
  "date": "Wed May 26 20:47:43 2021",
  "session_duration[s]": 192,
  "numbers_of_draws": [29],
  "invalid": [
    { "english": "concise", "polish": "zwi\u0105z\u0142y" },
    { "english": "entrance", "polish": "wejscie" },
    { "english": "humongous", "polish": "gigantyczny" },
    { "english": "astonished", "polish": "zdumiony" },
    { "english": "hesitation", "polish": "wahanie" },
    { "english": "on cloud nine", "polish": "w si\u00f3dmym niebie" }
  ],
  "valid": [
    {
      "english": "famished",
      "polish": "g\u0142odny (ale inaczej ni\u017c hungry) "
    },
    { "english": "despite", "polish": "pomimo" },
    { "english": "mortgage", "polish": "kredyt hipoteczny" },
    { "english": "i feel like", "polish": "mam ochote" },
    { "english": "genuine", "polish": "prawdziwe" },
    { "english": "epoch", "polish": "epoka" },
    { "english": "make yourself at home", "polish": "czuj sie jak w domu" },
    { "english": "devastated", "polish": "zdruzgotany" },
    { "english": "deviated", "polish": "odchylony/ odbiegaj\u0105cy" },
    { "english": "interest", "polish": "zainteresowanie, interes" },
    { "english": "attitude", "polish": "nastawienie " },
    { "english": "made an effort", "polish": "postara\u0142em si\u0119" },
    { "english": "thrilled", "polish": "zachwycony" },
    { "english": "intend to", "polish": "zamierza\u0107" },
    { "english": "cumbersome", "polish": "niewygodny, niepor\u0119czny" },
    { "english": "soil", "polish": "gleba" },
    { "english": "vital", "polish": "niezb\u0119dny" },
    { "english": "crucial", "polish": "istotny" },
    { "english": "it's baffling", "polish": "to jest zaskakujace" },
    { "english": "batch", "polish": "partia/cz\u0119\u015b\u0107" },
    { "english": "pay attention", "polish": "zwraca\u0107 uwage" },
    { "english": "plainly", "polish": "po prostu, wyra\u017anie" }
  ],
  "points_generated_during_session": {
    "attitude": 0,
    "it's baffling": 3,
    "batch": 3,
    "without a doubt": 2,
    "entrance": 0,
    "unaware": 3,
    "make yourself at home": 3,
    "deviated": -1,
    "hesitation": -4,
    "concise": -4,
    "intend to": -1,
    "made an effort": 2,
    "despite": 2,
    "plainly": 2,
    "genuine": 2,
    "mortgage": 2,
    "species": 1,
    "pay attention": 2,
    "magnitude": 1,
    "i feel like": 2,
    "epoch": 2,
    "soil": 2,
    "cumbersome": 2,
    "joy": 1,
    "humongous": -2,
    "astonished": -2,
    "on cloud nine": -2,
    "famished": 1,
    "devastated": 1,
    "interest": 1,
    "thrilled": 1,
    "vital": 1,
    "crucial": 1
  },
  "progress": {
    "deleted_words": [],
    "words_made_strong": [
      { "english": "make yourself at home", "polish": "czuj sie jak w domu" },
      { "english": "unaware", "polish": "nie\u015bwiadomy" },
      { "english": "batch", "polish": "partia/cz\u0119\u015b\u0107" },
      { "english": "it's baffling", "polish": "to jest zaskakujace" }
    ],
    "words_made_weak": [],
    "words_removed_from_strong": [],
    "words_removed_from_weak": []
  }
}
